{
    "simple_cta_component_1721724617.js": {
        "component_name": "simple_cta_component",
        "id": "simple_cta_component_1721724617",
        "type": "containerComponent",
        "metadata": {},
        "w": 5,
        "h": 8,
        "x": 0,
        "y": 15,
        "i": "2",
        "minW": 3,
        "maxW": 12,
        "minH": 1,
        "moved": false,
        "static": false,
        "isDraggable": true,
        "isResizable": true,
        "name": ""
    },
    "simple_hero_component_1721724617.js": {
        "component_name": "simple_hero_component",
        "id": "simple_hero_component_1721724617",
        "type": "containerComponent",
        "metadata": {},
        "w": 5,
        "h": 7,
        "x": 0,
        "y": 23,
        "i": "0",
        "minW": 3,
        "maxW": 12,
        "minH": 1,
        "moved": false,
        "static": false,
        "isDraggable": true,
        "isResizable": true,
        "name": ""
    },
    "simple_footer_component_1721724617.js": {
        "component_name": "simple_footer_component",
        "id": "simple_footer_component_1721724617",
        "type": "containerComponent",
        "metadata": {},
        "w": 5,
        "h": 7,
        "x": 0,
        "y": 8,
        "i": "1",
        "minW": 3,
        "maxW": 12,
        "minH": 1,
        "moved": false,
        "static": false,
        "isDraggable": true,
        "isResizable": true,
        "name": ""
    },
    "simple_cta_component_1721724702.js": {
        "id": "simple_cta_component-6aa6f530-49a6-c242-03c2-94477a3fb58b",
        "name": "simple_cta_component",
        "type": "containerComponent",
        "metadata": {},
        "w": 7,
        "h": 7,
        "x": "50",
        "y": "50",
        "i": "__dropping-elem__",
        "minW": 3,
        "maxW": 12,
        "minH": 1,
        "moved": false,
        "static": false,
        "isDraggable": true,
        "isResizable": true
    }
}